SitanfuCs224dShenduXuexiYuZiranyuyanChuliJiangyiFix1/README.md
SitanfuCs224dShenduXuexiYuZiranyuyanChuliJiangyiFix1/__init__.py
SitanfuCs224dShenduXuexiYuZiranyuyanChuliJiangyiFix1/__main__.py
SitanfuCs224dShenduXuexiYuZiranyuyanChuliJiangyiFix1/file.epub
SitanfuCs224dShenduXuexiYuZiranyuyanChuliJiangyiFix1/index.html
SitanfuCs224dShenduXuexiYuZiranyuyanChuliJiangyiFix1/css/__init__.py
SitanfuCs224dShenduXuexiYuZiranyuyanChuliJiangyiFix1/css/annotations.css
SitanfuCs224dShenduXuexiYuZiranyuyanChuliJiangyiFix1/css/main.css
SitanfuCs224dShenduXuexiYuZiranyuyanChuliJiangyiFix1/css/normalize.css
SitanfuCs224dShenduXuexiYuZiranyuyanChuliJiangyiFix1/css/popup.css
SitanfuCs224dShenduXuexiYuZiranyuyanChuliJiangyiFix1/font/__init__.py
SitanfuCs224dShenduXuexiYuZiranyuyanChuliJiangyiFix1/font/fontello.eot
SitanfuCs224dShenduXuexiYuZiranyuyanChuliJiangyiFix1/font/fontello.svg
SitanfuCs224dShenduXuexiYuZiranyuyanChuliJiangyiFix1/font/fontello.ttf
SitanfuCs224dShenduXuexiYuZiranyuyanChuliJiangyiFix1/font/fontello.woff
SitanfuCs224dShenduXuexiYuZiranyuyanChuliJiangyiFix1/img/__init__.py
SitanfuCs224dShenduXuexiYuZiranyuyanChuliJiangyiFix1/img/annotator-glyph-sprite.png
SitanfuCs224dShenduXuexiYuZiranyuyanChuliJiangyiFix1/img/annotator-icon-sprite.png
SitanfuCs224dShenduXuexiYuZiranyuyanChuliJiangyiFix1/img/apple-touch-icon.png
SitanfuCs224dShenduXuexiYuZiranyuyanChuliJiangyiFix1/img/cancelfullscreen.png
SitanfuCs224dShenduXuexiYuZiranyuyanChuliJiangyiFix1/img/close.png
SitanfuCs224dShenduXuexiYuZiranyuyanChuliJiangyiFix1/img/fullscreen.png
SitanfuCs224dShenduXuexiYuZiranyuyanChuliJiangyiFix1/img/loader.gif
SitanfuCs224dShenduXuexiYuZiranyuyanChuliJiangyiFix1/img/menu-icon.png
SitanfuCs224dShenduXuexiYuZiranyuyanChuliJiangyiFix1/img/save.png
SitanfuCs224dShenduXuexiYuZiranyuyanChuliJiangyiFix1/img/saved.png
SitanfuCs224dShenduXuexiYuZiranyuyanChuliJiangyiFix1/img/settings-s.png
SitanfuCs224dShenduXuexiYuZiranyuyanChuliJiangyiFix1/img/settings.png
sitanfu_cs224d_shendu_xuexi_yu_ziranyuyan_chuli_jiangyi_fix1-2024.3.4.0.dist-info/METADATA
sitanfu_cs224d_shendu_xuexi_yu_ziranyuyan_chuli_jiangyi_fix1-2024.3.4.0.dist-info/WHEEL
sitanfu_cs224d_shendu_xuexi_yu_ziranyuyan_chuli_jiangyi_fix1-2024.3.4.0.dist-info/entry_points.txt
sitanfu_cs224d_shendu_xuexi_yu_ziranyuyan_chuli_jiangyi_fix1-2024.3.4.0.dist-info/top_level.txt
sitanfu_cs224d_shendu_xuexi_yu_ziranyuyan_chuli_jiangyi_fix1-2024.3.4.0.dist-info/RECORD
